{"__symbolic":"module","version":1,"metadata":{"StoreModule":{"__symbolic":"class","decorators":[{"__symbolic":"call","expression":{"__symbolic":"reference","module":"@angular/core","name":"NgModule"},"arguments":[{"providers":[{"__symbolic":"reference","module":"./actions","name":"StoreActions"},{"__symbolic":"reference","module":"./store","name":"Store"},{"__symbolic":"reference","module":"./effects","name":"Effects"},{"provide":{"__symbolic":"reference","module":"./store","name":"STORE_INITIAL_STATE"},"useValue":{}},{"provide":{"__symbolic":"reference","module":"./store","name":"STORE_INITIAL_REDUCER"},"useValue":{}}]}]}]}},"exports":[{"from":"./actions"},{"from":"./utils"},{"from":"./effects"},{"from":"./observable"},{"from":"./store"}]}