[{"__symbolic":"module","version":3,"metadata":{"Wormhole":{"__symbolic":"reference","module":"./wormhole","name":"Wormhole"},"ConnectWormholeDirective":{"__symbolic":"reference","module":"./wormhole","name":"ConnectWormholeDirective"},"WormholeService":{"__symbolic":"reference","module":"./wormhole.service","name":"WormholeService"},"TemplateWormhole":{"__symbolic":"reference","module":"./wormhole","name":"TemplateWormhole"},"ComponentWormhole":{"__symbolic":"reference","module":"./wormhole","name":"ComponentWormhole"},"VCLWormholeModule":{"__symbolic":"class","decorators":[{"__symbolic":"error","message":"Function call not supported","line":16,"character":18}],"statics":{"withRootComponents":{"__symbolic":"function","parameters":["components"],"value":{"__symbolic":"error","message":"Function call not supported","line":33,"character":22}}}}}},{"__symbolic":"module","version":1,"metadata":{"Wormhole":{"__symbolic":"reference","module":"./wormhole","name":"Wormhole"},"ConnectWormholeDirective":{"__symbolic":"reference","module":"./wormhole","name":"ConnectWormholeDirective"},"WormholeService":{"__symbolic":"reference","module":"./wormhole.service","name":"WormholeService"},"TemplateWormhole":{"__symbolic":"reference","module":"./wormhole","name":"TemplateWormhole"},"ComponentWormhole":{"__symbolic":"reference","module":"./wormhole","name":"ComponentWormhole"},"VCLWormholeModule":{"__symbolic":"class","decorators":[{"__symbolic":"error","message":"Function call not supported","line":16,"character":18}],"statics":{"withRootComponents":{"__symbolic":"function","parameters":["components"],"value":{"__symbolic":"error","message":"Function call not supported","line":33,"character":22}}}}}}]